pulseapi_integration_rounding_motion/rounding_motion.py
pulseapi_integration_rounding_motion-0.0.5.dist-info/LICENSE
pulseapi_integration_rounding_motion-0.0.5.dist-info/METADATA
pulseapi_integration_rounding_motion-0.0.5.dist-info/WHEEL
pulseapi_integration_rounding_motion-0.0.5.dist-info/top_level.txt
pulseapi_integration_rounding_motion-0.0.5.dist-info/RECORD
