Metadata-Version: 2.1
Name: pulseapi-integration-rounding-motion
Version: 0.0.5
Summary: Move robot with blends
Home-page: https://github.com/Matskevichivan/Blend
Author: Matskevich
Author-email: matskevichivan98@gmail.com
License: UNKNOWN
Platform: UNKNOWN
Classifier: Programming Language :: Python :: 3
Classifier: License :: OSI Approved :: MIT License
Classifier: Operating System :: OS Independent
Requires-Python: >=3.6
Requires-Dist: pulse-api (>=1.6)
Requires-Dist: numpy (>=1.18)
Requires-Dist: pulseapi-integration (>=0.1.0)
